process_engine/__init__.py
process_engine/core/__init__.py
process_engine/core/base_client.py
process_engine/core/loop_helper.py
process_engine/external_task/__init__.py
process_engine/external_task/external_task_client.py
process_engine/external_task/external_task_worker.py
process_engine/external_task/functional_error.py
process_engine/notifications/__init__.py
process_engine/notifications/notification_client.py
process_engine/process_control/__init__.py
process_engine/process_control/process_control_client.py
process_engine/process_control/start_callback_type.py
process_engine/user_task/__init__.py
process_engine/user_task/user_task_client.py
tests/__init__.py
tests/helper_aiohttp.py
tests/core/__init__.py
tests/core/test_base_client.py
tests/core/test_loop_helper.py
tests/process_control/__init__.py
tests/process_control/test_process_control_client.py
process_engine-0.11.1.dist-info/METADATA
process_engine-0.11.1.dist-info/WHEEL
process_engine-0.11.1.dist-info/top_level.txt
process_engine-0.11.1.dist-info/RECORD
