Metadata-Version: 2.1
Name: process-engine
Version: 0.11.1
Summary: A Client for an process-engine.io hosted workflow engine.
Home-page: https://github.com/5minds/process_engine-python
Author: 5Minds IT-Solutions GmbH & Co. KG
Author-email: processengine@5minds.de
License: UNKNOWN
Keywords: workflow-engine processengine client bpmn
Platform: UNKNOWN
Classifier: Programming Language :: Python :: 3
Classifier: License :: OSI Approved :: MIT License
Classifier: Operating System :: OS Independent
